{
  "updated": "2026-07-15T22:29:25.560274+00:00",
  "source": "TradingView pre-market gappers (america)",
  "total_count": 7,
  "columns": [
    {
      "left": "symbol",
      "label": "Symbol",
      "fmt": "text"
    },
    {
      "left": "premarket_change",
      "label": "PM Chg %",
      "fmt": "pct"
    },
    {
      "left": "change_from_open",
      "label": "From Open %",
      "fmt": "pct"
    },
    {
      "left": "premarket_close",
      "label": "PM Price",
      "fmt": "price"
    },
    {
      "left": "premarket_volume",
      "label": "PM Vol",
      "fmt": "vol"
    },
    {
      "left": "float_shares_percent_current",
      "label": "Float %",
      "fmt": "pct"
    },
    {
      "left": "float_shares_outstanding_current",
      "label": "Float Sh",
      "fmt": "vol"
    },
    {
      "left": "market_cap_basic",
      "label": "Mkt Cap",
      "fmt": "money"
    },
    {
      "left": "sector",
      "label": "Sector",
      "fmt": "text"
    },
    {
      "left": "exchange.tr",
      "label": "Exch",
      "fmt": "text"
    }
  ],
  "rows": [
    {
      "_ticker": "NASDAQ:JTAI",
      "symbol": "JTAI",
      "premarket_change": 978.6341866087826,
      "change_from_open": -36.94779116465864,
      "premarket_close": 4.98,
      "premarket_volume": 15837467,
      "float_shares_percent_current": 85.7616,
      "float_shares_outstanding_current": 1219290.677136,
      "market_cap_basic": 4464203.7659137575,
      "sector": "Transportation",
      "exchange.tr": "NASDAQ"
    },
    {
      "_ticker": "NASDAQ:VIVS",
      "symbol": "VIVS",
      "premarket_change": 77.28797316722569,
      "change_from_open": -42.758389261744966,
      "premarket_close": 1.48,
      "premarket_volume": 48271710,
      "float_shares_percent_current": 87.33189999999999,
      "float_shares_outstanding_current": 2277581.01924,
      "market_cap_basic": 2224331.119190225,
      "sector": "Health Technology",
      "exchange.tr": "NASDAQ"
    },
    {
      "_ticker": "NASDAQ:ELVA",
      "symbol": "ELVA",
      "premarket_change": 56.527249683143225,
      "change_from_open": -3.6065573770491763,
      "premarket_close": 12.35,
      "premarket_volume": 5051108,
      "float_shares_percent_current": 67.3905,
      "float_shares_outstanding_current": 33363351.7875,
      "market_cap_basic": 582207993.721519,
      "sector": "Producer Manufacturing",
      "exchange.tr": "NASDAQ"
    },
    {
      "_ticker": "NASDAQ:KUST",
      "symbol": "KUST",
      "premarket_change": 47.55445544554455,
      "change_from_open": -12.080536912751674,
      "premarket_close": 1.4903,
      "premarket_volume": 54576169,
      "float_shares_percent_current": 91.98719999999999,
      "float_shares_outstanding_current": 576630.9619199999,
      "market_cap_basic": 821187.1188118813,
      "sector": "Commercial Services",
      "exchange.tr": "NASDAQ"
    },
    {
      "_ticker": "NASDAQ:SOBR",
      "symbol": "SOBR",
      "premarket_change": 42.73504273504274,
      "change_from_open": 23.214285714285708,
      "premarket_close": 1.67,
      "premarket_volume": 20540025,
      "float_shares_percent_current": 82.685,
      "float_shares_outstanding_current": 2320620.673,
      "market_cap_basic": 5809582.384615385,
      "sector": "Electronic Technology",
      "exchange.tr": "NASDAQ"
    },
    {
      "_ticker": "NASDAQ:ERNA",
      "symbol": "ERNA",
      "premarket_change": 41.419141914191435,
      "change_from_open": -20.91656874265569,
      "premarket_close": 8.57,
      "premarket_volume": 10239330,
      "float_shares_percent_current": 58.22110000000001,
      "float_shares_outstanding_current": 679050.15563,
      "market_cap_basic": 7849421.112211223,
      "sector": "Health Technology",
      "exchange.tr": "NASDAQ"
    },
    {
      "_ticker": "NASDAQ:AEHR",
      "symbol": "AEHR",
      "premarket_change": 36.78655742258019,
      "change_from_open": -10.559828842137431,
      "premarket_close": 98.5,
      "premarket_volume": 532733,
      "float_shares_percent_current": 94.3841,
      "float_shares_outstanding_current": 29686914.1253,
      "market_cap_basic": 2761281311.8597417,
      "sector": "Electronic Technology",
      "exchange.tr": "NASDAQ"
    }
  ]
}